Workbook

Sheet 01_Raw_Data
A1: TESCO PLC — Financial Analysis
A2: Five-Year Financial Performance Analysis
A3: £m unless otherwise stated
A4: Financial Metric | B4: FY2021/22 | C4: FY2022/23 | D4: FY2023/24 | E4: FY2024/25 | F4: FY2025/26
A6: INCOME STATEMENT
A8: Revenue | B8: 61344 | C8: 65322 | D8: 68187 | E8: 69916 | F8: 73712
A9: Operating Profit | B9: 2560 | C9: 1410 | D9: 2821 | E9: 2711 | F9: 2985
A10: Profit Before Tax | B10: 2033 | C10: 882 | D10: 2289 | E10: 2215 | F10: 2403
A11: Profit After Tax | B11: 1523 | C11: 658 | D11: 1764 | E11: 1604 | F11: 1787
A13: BALANCE SHEET
A15: Total Assets | B15: 49137 | C15: 45868 | D15: 47039 | E15: 38890 | F15: 39474
A16: Current Assets | B16: 11985 | C16: 12469 | D16: 16606 | E16: 8856 | F16: 8483
A17: Inventory | B17: 2339 | C17: 2510 | D17: 2635 | E17: 2768 | F17: 2840
A18: Cash & Cash Equivalents | B18: 2345 | C18: 2465 | D18: 2340 | E18: 2255 | F18: 2515
A19: Total Liabilities | B19: 33505 | C19: 33643 | D19: 35374 | E19: 27228 | F19: 28017
A20: Current Liabilities | B20: 15963 | C20: 17610 | D20: 20472 | E20: 13820 | F20: 14329
A21: Total Equity | B21: 15632 | C21: 12225 | D21: 11665 | E21: 11662 | F21: 11457
A22: Total Borrowings | B22: 7399 | C22: 7351 | D22: 7219 | E22: 6950 | F22: 7196
A24: CASH FLOW
A26: Retail Cash Generated from Operating Activities | B26: 3614 | C26: 3752 | D26: 3712
A27: Capex | B27: 1101 | C27: 1235 | D27: 1314 | E27: 1457 | F27: 1511
A28: Free Cash Flow | B28: 2277 | C28: 2133 | D28: 2063 | E28: 1750 | F28: 1957
A30: OTHER METRICS
A32: Adjusted Operating Profit | B32: 2825 | C32: 2509 | D32: 2829 | E32: 3128 | F32: 3152
A33: Diluted EPS (Pence) | B33: 19.64 | C33: 8.81 | D33: 24.53 | E33: 23.13 | F33: 27.1
A34: Dividend Per Share (pence) | B34: 10.9 | C34: 10.9 | D34: 12.1 | E34: 13.7 | F34: 14.5
A37: Methodology note:

Sheet 02_Performance
A1: TESCO PLC — Performance Analysis
A2: Five-Year Revenue, Profitability & Growth Analysis
A3: £m unless otherwise stated
A5: Performance Metric | B5: FY2021/22 | C5: FY2022/23 | D5: FY2023/24 | E5: FY2024/25 | F5: FY2025/26 | I5: FY21/22 | J5: FY22/23 | K5: FY23/24 | L5: FY24/25 | M5: FY25/26
H6: Revenue | I6: ='01_Raw_Data'!B8 -> 61344 | J6: ='01_Raw_Data'!C8 -> 65322 | K6: ='01_Raw_Data'!D8 -> 68187 | L6: ='01_Raw_Data'!E8 -> 69916 | M6: ='01_Raw_Data'!F8 -> 73712
A7: FINANCIAL PERFORMANCE | H7: Adjusted Operating Profit | I7: ='01_Raw_Data'!B32 -> 2825 | J7: ='01_Raw_Data'!C32 -> 2509 | K7: ='01_Raw_Data'!D32 -> 2829 | L7: ='01_Raw_Data'!E32 -> 3128 | M7: ='01_Raw_Data'!F32 -> 3152
A9: Revenue | B9: ='01_Raw_Data'!B8 -> 61344 | C9: ='01_Raw_Data'!C8 -> 65322 | D9: ='01_Raw_Data'!D8 -> 68187 | E9: ='01_Raw_Data'!E8 -> 69916 | F9: ='01_Raw_Data'!F8 -> 73712
A10: Revenue Growth % | C10: =(C9/B9)-1 -> 0.064847418 | D10: =(D9/C9)-1 -> 0.043859649 | E10: =(E9/D9)-1 -> 0.02535674 | F10: =(F9/E9)-1 -> 0.054293724
A12: Operating Profit | B12: ='01_Raw_Data'!B9 -> 2560 | C12: ='01_Raw_Data'!C9 -> 1410 | D12: ='01_Raw_Data'!D9 -> 2821 | E12: ='01_Raw_Data'!E9 -> 2711 | F12: ='01_Raw_Data'!F9 -> 2985
A13: Operating Profit Growth % | C13: =(C12/B12)-1 -> -0.44921875 | D13: =(D12/C12)-1 -> 1.0007092 | E13: =(E12/D12)-1 -> -0.038993265 | F13: =(F12/E12)-1 -> 0.10106972
A15: Adjusted Operating Profit | B15: ='01_Raw_Data'!B32 -> 2825 | C15: ='01_Raw_Data'!C32 -> 2509 | D15: ='01_Raw_Data'!D32 -> 2829 | E15: ='01_Raw_Data'!E32 -> 3128 | F15: ='01_Raw_Data'!F32 -> 3152
A16: Adjusted Operating Profit Growth % | C16: =(C15/B15)-1 -> -0.11185841 | D16: =(D15/C15)-1 -> 0.12754085 | E16: =(E15/D15)-1 -> 0.10569106 | F16: =(F15/E15)-1 -> 0.0076726343
A18: Profit Before Tax | B18: ='01_Raw_Data'!B10 -> 2033 | C18: ='01_Raw_Data'!C10 -> 882 | D18: ='01_Raw_Data'!D10 -> 2289 | E18: ='01_Raw_Data'!E10 -> 2215 | F18: ='01_Raw_Data'!F10 -> 2403
A19: Profit After Tax | B19: ='01_Raw_Data'!B11 -> 1523 | C19: ='01_Raw_Data'!C11 -> 658 | D19: ='01_Raw_Data'!D11 -> 1764 | E19: ='01_Raw_Data'!E11 -> 1604 | F19: ='01_Raw_Data'!F11 -> 1787
A21: PROFITABILITY
A23: Operating Margin % | B23: =B12/B9 -> 0.041731873 | C23: =C12/C9 -> 0.021585377 | D23: =D12/D9 -> 0.041371522 | E23: =E12/E9 -> 0.038775102 | F23: =F12/F9 -> 0.040495442
A24: Adjusted Operating Margin % | B24: =B15/B9 -> 0.046051774 | C24: =C15/C9 -> 0.038409724 | D24: =D15/D9 -> 0.041488847 | E24: =E15/E9 -> 0.044739402 | F24: =F15/F9 -> 0.042761016
A25: Net Profit Margin % | B25: =B19/B9 -> 0.024827204 | C25: =C19/C9 -> 0.010073176 | D25: =D19/D9 -> 0.025870034 | E25: =E19/E9 -> 0.022941816 | F25: =F19/F9 -> 0.024243
A27: FIVE-YEAR GROWTH
A29: Revenue CAGR | B29: =(F9/B9)^(1/4)-1 -> 0.046987571
A30: Operating Profit CAGR | B30: =(F12/B12)^(1/4)-1 -> 0.039144857 | I30: FY21/22 | J30: FY22/23 | K30: FY23/24 | L30: FY24/25 | M30: FY25/26
A31: Adjusted Operating Profit CAGR | B31: =(F15/B15)^(1/4)-1 -> 0.02776054 | H31: Operating Margin | I31: =B23 -> 0.041731873 | J31: =C23 -> 0.021585377 | K31: =D23 -> 0.041371522 | L31: =E23 -> 0.038775102 | M31: =F23 -> 0.040495442
A32: Profit After Tax CAGR | B32: =(F19/B19)^(1/4)-1 -> 0.040773348 | H32: Adjusted Operating Margin | I32: =B24 -> 0.046051774 | J32: =C24 -> 0.038409724 | K32: =D24 -> 0.041488847 | L32: =E24 -> 0.044739402 | M32: =F24 -> 0.042761016
H33: Net Profit Margin | I33: =B25 -> 0.024827204 | J33: =C25 -> 0.010073176 | K33: =D25 -> 0.025870034 | L33: =E25 -> 0.022941816 | M33: =F25 -> 0.024243
I54: FY22/23 | J54: FY23/24 | K54: FY24/25 | L54: FY25/26
H55: Revenue Growth | I55: =C10 -> 0.064847418 | J55: =D10 -> 0.043859649 | K55: =E10 -> 0.02535674 | L55: =F10 -> 0.054293724
H56: Adjusted Operating Profit Growth | I56: =C16 -> -0.11185841 | J56: =D16 -> 0.12754085 | K56: =E16 -> 0.10569106 | L56: =F16 -> 0.0076726343
B75: KEY PERFORMANCE INSIGHTS

Sheet 03_Balance_Sheet
A1: TESCO PLC — Balance Sheet Analysis
A2: Five-Year Liquidity, Leverage & Financial Position Analysis
A3: £m unless otherwise stated
A5: Balance Sheet Metric | B5: FY21/22 | C5: FY22/23 | D5: FY23/24 | E5: FY24/25 | F5: FY25/26
A7: FINANCIAL POSITION
A8: Total Assets | B8: ='01_Raw_Data'!B15 -> 49137 | C8: ='01_Raw_Data'!C15 -> 45868 | D8: ='01_Raw_Data'!D15 -> 47039 | E8: ='01_Raw_Data'!E15 -> 38890 | F8: ='01_Raw_Data'!F15 -> 39474 | J8: FY21/22 | K8: FY22/23 | L8: FY23/24 | M8: FY24/25 | N8: FY25/26
A9: Total Asset Growth % | C9: =(C8/B8)-1 -> -0.066528278 | D9: =(D8/C8)-1 -> 0.025529781 | E9: =(E8/D8)-1 -> -0.17323923 | F9: =(F8/E8)-1 -> 0.015016714 | I9: Current Ratio | J9: =B26 -> 0.75079872 | K9: =C26 -> 0.7080636 | L9: =D26 -> 0.8111567 | M9: =E26 -> 0.64081042 | N9: =F26 -> 0.59201619
I10: Quick Ratio | J10: =B27 -> 0.60427238 | K10: =C27 -> 0.56553095 | L10: =D27 -> 0.68244431 | M10: =E27 -> 0.44052098 | N10: =F27 -> 0.39381674
A11: Current Assets | B11: ='01_Raw_Data'!B16 -> 11985 | C11: ='01_Raw_Data'!C16 -> 12469 | D11: ='01_Raw_Data'!D16 -> 16606 | E11: ='01_Raw_Data'!E16 -> 8856 | F11: ='01_Raw_Data'!F16 -> 8483 | I11: Cash Ratio | J11: =B28 -> 0.14690221 | K11: =C28 -> 0.13997729 | L11: =D28 -> 0.11430246 | M11: =E28 -> 0.16316932 | N11: =F28 -> 0.17551818
A12: Inventory | B12: ='01_Raw_Data'!B17 -> 2339 | C12: ='01_Raw_Data'!C17 -> 2510 | D12: ='01_Raw_Data'!D17 -> 2635 | E12: ='01_Raw_Data'!E17 -> 2768 | F12: ='01_Raw_Data'!F17 -> 2840
A13: Cash & Cash Equivalents | B13: ='01_Raw_Data'!B18 -> 2345 | C13: ='01_Raw_Data'!C18 -> 2465 | D13: ='01_Raw_Data'!D18 -> 2340 | E13: ='01_Raw_Data'!E18 -> 2255 | F13: ='01_Raw_Data'!F18 -> 2515
A15: Total Liabilities | B15: ='01_Raw_Data'!B19 -> 33505 | C15: ='01_Raw_Data'!C19 -> 33643 | D15: ='01_Raw_Data'!D19 -> 35374 | E15: ='01_Raw_Data'!E19 -> 27228 | F15: ='01_Raw_Data'!F19 -> 28017
A16: Current Liabilities | B16: ='01_Raw_Data'!B20 -> 15963 | C16: ='01_Raw_Data'!C20 -> 17610 | D16: ='01_Raw_Data'!D20 -> 20472 | E16: ='01_Raw_Data'!E20 -> 13820 | F16: ='01_Raw_Data'!F20 -> 14329
A18: Total Equity | B18: ='01_Raw_Data'!B21 -> 15632 | C18: ='01_Raw_Data'!C21 -> 12225 | D18: ='01_Raw_Data'!D21 -> 11665 | E18: ='01_Raw_Data'!E21 -> 11662 | F18: ='01_Raw_Data'!F21 -> 11457
A20: Total Borrowings | B20: ='01_Raw_Data'!B22 -> 7399 | C20: ='01_Raw_Data'!C22 -> 7351 | D20: ='01_Raw_Data'!D22 -> 7219 | E20: ='01_Raw_Data'!E22 -> 6950 | F20: ='01_Raw_Data'!F22 -> 7196
A21: Borrowings Growth % | C21: =(C20/B20)-1 -> -0.0064873632 | D21: =(D20/C20)-1 -> -0.017956741 | E21: =(E20/D20)-1 -> -0.037262779 | F21: =(F20/E20)-1 -> 0.035395683
A24: LIQUIDITY
A26: Current Ratio | B26: =B11/B16 -> 0.75079872 | C26: =C11/C16 -> 0.7080636 | D26: =D11/D16 -> 0.8111567 | E26: =E11/E16 -> 0.64081042 | F26: =F11/F16 -> 0.59201619
A27: Quick Ratio | B27: =(B11-B12)/B16 -> 0.60427238 | C27: =(C11-C12)/C16 -> 0.56553095 | D27: =(D11-D12)/D16 -> 0.68244431 | E27: =(E11-E12)/E16 -> 0.44052098 | F27: =(F11-F12)/F16 -> 0.39381674
A28: Cash Ratio | B28: =B13/B16 -> 0.14690221 | C28: =C13/C16 -> 0.13997729 | D28: =D13/D16 -> 0.11430246 | E28: =E13/E16 -> 0.16316932 | F28: =F13/F16 -> 0.17551818
A30: LEVERAGE & CAPITAL STRUCTURE
A32: Borrowings to Equity | B32: =B20/B18 -> 0.47332395 | C32: =C20/C18 -> 0.60130879 | D32: =D20/D18 -> 0.61885984 | E32: =E20/E18 -> 0.59595267 | F32: =F20/F18 -> 0.62808763 | J32: FY21/22 | K32: FY22/23 | L32: FY23/24 | M32: FY24/25 | N32: FY25/26
A33: Liabilities to Assets % | B33: =B15/B8 -> 0.68186906 | C33: =C15/C8 -> 0.73347432 | D33: =D15/D8 -> 0.75201429 | E33: =E15/E8 -> 0.70012857 | F33: =F15/F8 -> 0.70975832 | I33: Liabilities to Assets | J33: =B33 -> 0.68186906 | K33: =C33 -> 0.73347432 | L33: =D33 -> 0.75201429 | M33: =E33 -> 0.70012857 | N33: =F33 -> 0.70975832
A34: Equity Ratio % | B34: =B18/B8 -> 0.31813094 | C34: =C18/C8 -> 0.26652568 | D34: =D18/D8 -> 0.24798571 | E34: =E18/E8 -> 0.29987143 | F34: =F18/F8 -> 0.29024168 | I34: Equity Ratio | J34: =B34 -> 0.31813094 | K34: =C34 -> 0.26652568 | L34: =D34 -> 0.24798571 | M34: =E34 -> 0.29987143 | N34: =F34 -> 0.29024168
A54: KEY BALANCE SHEET INSIGHTS

Sheet 04_Cash_Flow
A1: TESCO PLC — Cash Flow Analysis
A2: Five-Year Cash Generation & Investment Analysis
A3: £m unless otherwise stated
A5: Cash Flow Metric | B5: FY21/22 | C5: FY22/23 | D5: FY23/24 | E5: FY24/25 | F5: FY25/26 | I5: FY21/22 | J5: FY22/23 | K5: FY23/24 | L5: FY24/25 | M5: FY25/26
H6: Retail Free Cash Flow | I6: =B9 -> 2277 | J6: =C9 -> 2133 | K6: =D9 -> 2063 | L6: =E9 -> 1750 | M6: =F9 -> 1957
A7: CASH FLOW PERFORMANCE | H7: Capex | I7: =B11 -> 1101 | J7: =C11 -> 1235 | K7: =D11 -> 1314 | L7: =E11 -> 1457 | M7: =F11 -> 1511
A9: Retail Free Cash Flow | B9: ='01_Raw_Data'!B28 -> 2277 | C9: ='01_Raw_Data'!C28 -> 2133 | D9: ='01_Raw_Data'!D28 -> 2063 | E9: ='01_Raw_Data'!E28 -> 1750 | F9: ='01_Raw_Data'!F28 -> 1957
A10: Free Cash Flow Growth % | C10: =(C9/B9)-1 -> -0.063241107 | D10: =(D9/C9)-1 -> -0.032817628 | E10: =(E9/D9)-1 -> -0.15172079 | F10: =(F9/E9)-1 -> 0.11828571
A11: Capex | B11: ='01_Raw_Data'!B27 -> 1101 | C11: ='01_Raw_Data'!C27 -> 1235 | D11: ='01_Raw_Data'!D27 -> 1314 | E11: ='01_Raw_Data'!E27 -> 1457 | F11: ='01_Raw_Data'!F27 -> 1511
A12: Capex Growth % | C12: =(C11/B11)-1 -> 0.12170754 | D12: =(D11/C11)-1 -> 0.063967611 | E12: =(E11/D11)-1 -> 0.10882801 | F12: =(F11/E11)-1 -> 0.037062457
A14: CASH FLOW RATIOS
A16: Free Cash Flow Margin % | B16: =B9/'02_Performance'!B9 -> 0.037118545 | C16: =C9/'02_Performance'!C9 -> 0.032653624 | D16: =D9/'02_Performance'!D9 -> 0.030255034 | E16: =E9/'02_Performance'!E9 -> 0.025030036 | F16: =F9/'02_Performance'!F9 -> 0.026549273
A17: Capex to Revenue % | B17: =B11/'02_Performance'!B9 -> 0.017947966 | C17: =C11/'02_Performance'!C9 -> 0.018906341 | D17: =D11/'02_Performance'!D9 -> 0.019270535 | E17: =E11/'02_Performance'!E9 -> 0.020839293 | F17: =F11/'02_Performance'!F9 -> 0.020498698
A18: Free Cash Flow to Adjusted Operating Profit % | B18: =B9/'02_Performance'!B15 -> 0.8060177 | C18: =C9/'02_Performance'!C15 -> 0.8501395 | D18: =D9/'02_Performance'!D15 -> 0.72923294 | E18: =E9/'02_Performance'!E15 -> 0.55946292 | F18: =F9/'02_Performance'!F15 -> 0.62087563
A25: KEY CASH FLOW INSIGHTS

Sheet 05_Ratios
A1: TESCO PLC — Financial Ratio Analysis
A2: Five-Year Financial Health & Ratio Summary
A4: Ratio | B4: FY21/22 | C4: FY22/23 | D4: FY23/24 | E4: FY24/25 | F4: FY25/26 | H4: 5-Year Trend
A6: PROFITABILITY
H7: Ratio | I7: 5-Year Trend
A8: Operating Margin % | B8: ='02_Performance'!B23 -> 0.041731873 | C8: ='02_Performance'!C23 -> 0.021585377 | D8: ='02_Performance'!D23 -> 0.041371522 | E8: ='02_Performance'!E23 -> 0.038775102 | F8: ='02_Performance'!F23 -> 0.040495442 | H8: Operating Margin | I8: Stable
A9: Adjusted Operating Margin % | B9: ='02_Performance'!B24 -> 0.046051774 | C9: ='02_Performance'!C24 -> 0.038409724 | D9: ='02_Performance'!D24 -> 0.041488847 | E9: ='02_Performance'!E24 -> 0.044739402 | F9: ='02_Performance'!F24 -> 0.042761016 | H9: Adjusted Operating Margin | I9: Slight decline
A10: Net Profit Margin % | B10: ='02_Performance'!B25 -> 0.024827204 | C10: ='02_Performance'!C25 -> 0.010073176 | D10: ='02_Performance'!D25 -> 0.025870034 | E10: ='02_Performance'!E25 -> 0.022941816 | F10: ='02_Performance'!F25 -> 0.024243 | H10: Net Profit Margin | I10: Broadly stable
H11: Current Ratio | I11: Declining
A12: LIQUIDITY | H12: Quick Ratio | I12: Declining
H13: Cash Ratio | I13: Improving
A14: Current Ratio | B14: ='03_Balance_Sheet'!B26 -> 0.75079872 | C14: ='03_Balance_Sheet'!C26 -> 0.7080636 | D14: ='03_Balance_Sheet'!D26 -> 0.8111567 | E14: ='03_Balance_Sheet'!E26 -> 0.64081042 | F14: ='03_Balance_Sheet'!F26 -> 0.59201619 | H14: Borrowings to Equity | I14: Increasing
A15: Quick Ratio | B15: ='03_Balance_Sheet'!B27 -> 0.60427238 | C15: ='03_Balance_Sheet'!C27 -> 0.56553095 | D15: ='03_Balance_Sheet'!D27 -> 0.68244431 | E15: ='03_Balance_Sheet'!E27 -> 0.44052098 | F15: ='03_Balance_Sheet'!F27 -> 0.39381674 | H15: Liabilities to Assets | I15: Increasing
A16: Cash Ratio | B16: ='03_Balance_Sheet'!B28 -> 0.14690221 | C16: ='03_Balance_Sheet'!C28 -> 0.13997729 | D16: ='03_Balance_Sheet'!D28 -> 0.11430246 | E16: ='03_Balance_Sheet'!E28 -> 0.16316932 | F16: ='03_Balance_Sheet'!F28 -> 0.17551818 | H16: Equity Ratio | I16: Declining
H17: FCF Margin | I17: Declining
A18: LEVERAGE | H18: Capex to Revenue | I18: Increasing
H19: FCF / Adjusted OP | I19: Declining
A20: Borrowings to Equity | B20: ='03_Balance_Sheet'!B32 -> 0.47332395 | C20: ='03_Balance_Sheet'!C32 -> 0.60130879 | D20: ='03_Balance_Sheet'!D32 -> 0.61885984 | E20: ='03_Balance_Sheet'!E32 -> 0.59595267 | F20: ='03_Balance_Sheet'!F32 -> 0.62808763
A21: Liabilities to Assets % | B21: ='03_Balance_Sheet'!B33 -> 0.68186906 | C21: ='03_Balance_Sheet'!C33 -> 0.73347432 | D21: ='03_Balance_Sheet'!D33 -> 0.75201429 | E21: ='03_Balance_Sheet'!E33 -> 0.70012857 | F21: ='03_Balance_Sheet'!F33 -> 0.70975832
A22: Equity Ratio % | B22: ='03_Balance_Sheet'!B34 -> 0.31813094 | C22: ='03_Balance_Sheet'!C34 -> 0.26652568 | D22: ='03_Balance_Sheet'!D34 -> 0.24798571 | E22: ='03_Balance_Sheet'!E34 -> 0.29987143 | F22: ='03_Balance_Sheet'!F34 -> 0.29024168
A24: CASH FLOW
A26: Free Cash Flow Margin % | B26: ='04_Cash_Flow'!B16 -> 0.037118545 | C26: ='04_Cash_Flow'!C16 -> 0.032653624 | D26: ='04_Cash_Flow'!D16 -> 0.030255034 | E26: ='04_Cash_Flow'!E16 -> 0.025030036 | F26: ='04_Cash_Flow'!F16 -> 0.026549273
A27: Capex to Revenue % | B27: ='04_Cash_Flow'!B17 -> 0.017947966 | C27: ='04_Cash_Flow'!C17 -> 0.018906341 | D27: ='04_Cash_Flow'!D17 -> 0.019270535 | E27: ='04_Cash_Flow'!E17 -> 0.020839293 | F27: ='04_Cash_Flow'!F17 -> 0.020498698
A28: FCF to Adjusted Operating Profit % | B28: ='04_Cash_Flow'!B18 -> 0.8060177 | C28: ='04_Cash_Flow'!C18 -> 0.8501395 | D28: ='04_Cash_Flow'!D18 -> 0.72923294 | E28: ='04_Cash_Flow'!E18 -> 0.55946292 | F28: ='04_Cash_Flow'!F18 -> 0.62087563
A32: FINANCIAL HEALTH SUMMARY

Sheet 06_Dashboard
A1: TESCO PLC
A2: 5-YEAR FINANCIAL PERFORMANCE DASHBOARD
A3: FY2021/22 — FY2025/26
A5: Revenue | B5: Adjusted Operating Profit | C5: Free Cash Flow | D5: Adjusted Operating Margin
A6: ='02_Performance'!F9/1000 -> 73.712 | B6: ='02_Performance'!F15/1000 -> 3.152 | C6: ='04_Cash_Flow'!F9/1000 -> 1.957 | D6: ='02_Performance'!F24 -> 0.042761016
A7: ='02_Performance'!F10 -> 0.054293724 | B7: ='02_Performance'!F16 -> 0.0076726343 | C7: ='04_Cash_Flow'!F10 -> 0.11828571 | D7: =('02_Performance'!F24-'02_Performance'!E24)*100 -> -0.19783857
D29: FINANCIAL HEALTH — FY2025/26
D31: Current Ratio | E31: ='03_Balance_Sheet'!F26 -> 0.59201619
D32: Borrowings to Equity | E32: ='03_Balance_Sheet'!F32 -> 0.62808763
D33: FCF Margin | E33: ='04_Cash_Flow'!$F$16 -> 0.026549273
D34: Adjusted Operating Margin | E34: ='02_Performance'!$F$24 -> 0.042761016
A38: KEY INSIGHTS
A40: Revenue: Increased from £61.3bn to £73.7bn over five years, representing approximately 4.7% CAGR.
A41: Profitability: Adjusted operating profitability recovered following the FY2022/23 decline, with FY2025/26 adjusted operating margin at 4.3%.
A42: Cash Generation: Free cash flow recovered 11.8% YoY to £1.96bn in FY2025/26 following three consecutive annual declines.
A43: Financial Position: Headline liquidity weakened over the period, with the current ratio declining from 0.76 to 0.59, while borrowings-to-equity increased from 0.47x to 0.63x.
B45: Source: Tesco PLC annual reports and preliminary results; author calculations.

Sheet 07_Key_Findings
A1: TESCO PLC — KEY FINDINGS & ANALYST CONCLUSION
A2: Five-Year Financial Performance Review | FY2021/22 — FY2025/26
A3: £m unless otherwise stated
A6: EXECUTIVE SUMMARY
A20: KEY STRENGTHS
A44: RISKS & WATCHPOINTS
A70: Five-Year Scorecard
A72: Area | B72: Five-Year Assessment
A73: Revenue Growth | B73: Positive
A74: Profitability | B74: Recovered / Positive
A75: Cash Generation | B75: Positive, but below earlier levels
A76: Liquidity | B76: Weakened
A77: Borrowings | B77: Relatively Stable
A78: Capital Investment | B78: Increasing
A79: Overall Financial Performance | B79: Resilient
A84: Final Analyst Conclusion
A104: Source: Tesco PLC annual reports and preliminary results; author calculations.
A108: Note: This analysis is prepared for educational and portfolio purposes and does not constitute investment advice.
